glassjar/constants.py
glassjar/db.py
glassjar/exceptions.py
glassjar/field.py
glassjar/model.py
glassjar-0.1.1.dist-info/LICENSE
glassjar-0.1.1.dist-info/METADATA
glassjar-0.1.1.dist-info/WHEEL
glassjar-0.1.1.dist-info/top_level.txt
glassjar-0.1.1.dist-info/RECORD
