Metadata-Version: 2.1
Name: glassjar
Version: 0.1.1
Summary: Pickled database that provide Object-Relational Mapper.
Home-page: https://github.com/furkanonder/glassjar/
Author: Furkan Onder
Author-email: furkanonder@protonmail.com
License: MIT
Keywords: database,pickled database,orm
Classifier: Development Status :: 2 - Pre-Alpha
Classifier: License :: OSI Approved :: MIT License
Classifier: Programming Language :: Python :: 3
Classifier: Programming Language :: Python :: 3 :: Only
Classifier: Programming Language :: Python :: 3.8
Classifier: Programming Language :: Python :: 3.9
Classifier: Programming Language :: Python :: 3.10
Classifier: Programming Language :: Python :: 3.11
Classifier: Topic :: Software Development :: Libraries :: Python Modules
Classifier: Topic :: Utilities
Classifier: Operating System :: OS Independent 
Requires-Python: >=3.8
License-File: LICENSE
